pyhomeworks/__init__.py
pyhomeworks/exceptions.py
pyhomeworks/py.typed
pyhomeworks/pyhomeworks.py
pyhomeworks-1.1.1.dist-info/LICENSE
pyhomeworks-1.1.1.dist-info/METADATA
pyhomeworks-1.1.1.dist-info/WHEEL
pyhomeworks-1.1.1.dist-info/top_level.txt
pyhomeworks-1.1.1.dist-info/zip-safe
pyhomeworks-1.1.1.dist-info/RECORD
