Metadata-Version: 2.1
Name: pyhomeworks
Version: 1.1.1
Summary: Lutron Homeworks Series 4 and 8 interface over Ethernet
Author-email: Michael Dubno <michael@dubno.com>
License: MIT
Project-URL: Homepage, https://github.com/dubnom/pyhomeworks
Platform: any
Classifier: Programming Language :: Python :: 3
Classifier: License :: OSI Approved :: MIT License
Classifier: Operating System :: OS Independent
Requires-Python: >=3.12.0
License-File: LICENSE
